LICENSE
README.md
setup.py
fr1997_mode/__init__.py
fr1997_mode/mode_func/__init__.py
fr1997_mode/mode_func/all_func.py
fr1997_mode/mode_func/base_class.py
fr1997_mode/mode_func/base_mode_class.py
fr1997_mode/mode_func/cache_class.py
fr1997_mode/mode_func/cos_class.py
fr1997_mode/mode_func/data_class.py
fr1997_mode/mode_func/django_class.py
fr1997_mode/mode_func/douyin_class.py
fr1997_mode/mode_func/es_class.py
fr1997_mode/mode_func/feishu_class.py
fr1997_mode/mode_func/func_class.py
fr1997_mode/mode_func/gy_class.py
fr1997_mode/mode_func/http_class.py
fr1997_mode/mode_func/mysql_class.py
fr1997_mode/mode_func/out_config.py
fr1997_mode/mode_func/pgsql_class.py
fr1997_mode/mode_func/redis_class.py
fr1997_mode/mode_func/spider_class.py
fr1997_mode/mode_func/text_class.py
fr1997_mode/mode_func/time_class.py
fr1997_mode/mode_func/weixin_class.py
fr1997_mode/mode_func/xhs_class.py
fr1997_mode/mode_func/zhihu_class.py
fr1997_mode/mode_static/__init__.py
fr1997_mode/mode_static/city.py
fr1997_mode/mode_static/good.py
fr1997_mode/mode_static/good_bad.py
fr1997_mode/mode_static/trade.py
fr1997v011.egg-info/PKG-INFO
fr1997v011.egg-info/SOURCES.txt
fr1997v011.egg-info/dependency_links.txt
fr1997v011.egg-info/not-zip-safe
fr1997v011.egg-info/top_level.txt