Metadata-Version: 2.1
Name: fr1997v011
Version: 26.1.19.1
Summary: fr1997 all func
Home-page: 
Author: fr1997
Author-email: 3084447185@qq.com
License: MIT
License-File: LICENSE
